{
  "SPY": {
    "currentPrice": 741.6,
    "previousClose": 758.54,
    "priceChange": -16.93999999999994,
    "priceChangePercent": -2.233237535265107,
    "currency": "USD",
    "lastUpdate": "2026-06-08T18:15:52.236Z"
  },
  "TSM": {
    "currentPrice": 428.84,
    "previousClose": 435.63,
    "priceChange": -6.7900000000000205,
    "priceChangePercent": -1.5586621674356724,
    "currency": "USD",
    "lastUpdate": "2026-06-08T18:15:52.606Z"
  },
  "TBLA": {
    "currentPrice": 4.555,
    "previousClose": 4.95,
    "priceChange": -0.39500000000000046,
    "priceChangePercent": -7.979797979797988,
    "currency": "USD",
    "lastUpdate": "2026-06-08T18:15:52.951Z"
  },
  "TLRY": {
    "currentPrice": 5.06,
    "previousClose": 5.49,
    "priceChange": -0.4300000000000006,
    "priceChangePercent": -7.832422586520958,
    "currency": "USD",
    "lastUpdate": "2026-06-08T18:15:53.292Z"
  },
  "XLE": {
    "currentPrice": 58.445,
    "previousClose": 57.3,
    "priceChange": 1.1450000000000031,
    "priceChangePercent": 1.9982547993019253,
    "currency": "USD",
    "lastUpdate": "2026-06-08T18:15:53.673Z"
  },
  "AML.L": {
    "currentPrice": 0.4138,
    "previousClose": 0.4522,
    "priceChange": -0.03839999999999999,
    "priceChangePercent": -8.491817779743474,
    "currency": "GBP",
    "lastUpdate": "2026-06-08T18:15:54.030Z"
  }
}